srtk/__init__.py
srtk/cli.py
srtk/link.py
srtk/preprocess.py
srtk/retrieve.py
srtk/train.py
srtk/utils.py
srtk/visualize.py
srtk/entity_linking/__init__.py
srtk/entity_linking/dbpedia.py
srtk/entity_linking/freebase.py
srtk/entity_linking/linker_base.py
srtk/entity_linking/wikidata.py
srtk/knowledge_graph/__init__.py
srtk/knowledge_graph/dbpedia.py
srtk/knowledge_graph/freebase.py
srtk/knowledge_graph/graph_base.py
srtk/knowledge_graph/utils.py
srtk/knowledge_graph/wikidata.py
srtk/preprocessing/__init__.py
srtk/preprocessing/load_dataset.py
srtk/preprocessing/merge_ground.py
srtk/preprocessing/negative_sampling.py
srtk/preprocessing/score_path.py
srtk/preprocessing/search_path.py
srtk/scorer/__init__.py
srtk/scorer/encoder.py
srtk/scorer/scorer.py
srtk-0.0.7.dist-info/METADATA
srtk-0.0.7.dist-info/WHEEL
srtk-0.0.7.dist-info/entry_points.txt
srtk-0.0.7.dist-info/licenses/LICENSE
srtk-0.0.7.dist-info/RECORD
