Metadata-Version: 2.1
Name: srtk
Version: 0.0.7
Summary: A toolkit for semantic-relevant subgraph retrieval from large-scale knowledge graphs.
Project-URL: Homepage, https://github.com/happen2me/subgraph-retrieval-toolkit
Project-URL: Bug Tracker, https://github.com/happen2me/subgraph-retrieval-toolkit/issues
Author-email: Yuanchun Shen <y.c.shen@tum.de>
License-File: LICENSE
Classifier: License :: OSI Approved :: MIT License
Classifier: Operating System :: OS Independent
Classifier: Programming Language :: Python :: 3
Requires-Python: >=3.6
Requires-Dist: beautifulsoup4
Requires-Dist: datasets
Requires-Dist: lightning
Requires-Dist: pyvis
Requires-Dist: sparqlwrapper
Requires-Dist: srsly
Requires-Dist: tqdm
Requires-Dist: transformers
Requires-Dist: wikimapper
